{
  "development": {
    "username": "hp",
    "password": "123",
    "database": "zadanie",
    "host": "127.0.0.1",
    "dialect": "postgres",
    "seedStorage": "sequelize",
    "seedStorageTableName": "SequelizeData"
  },
  "test": {
    "username": "root",
    "password": null,
    "database": "database_test",
    "host": "127.0.0.1",
    "dialect": "mysql"
  },
  "production": {
    "username": "root",
    "password": null,
    "database": "database_production",
    "host": "127.0.0.1",
    "dialect": "mysql"
  }
}
